gamepadx/__init__.py
gamepadx/commons.py
gamepadx/gamepad.py
gamepadx/vigem/ViGEmClient.dll
gamepadx/vigem/__init__.py
gamepadx/vigem/lib.py
gamepadx-1.0.1.dist-info/LICENSE
gamepadx-1.0.1.dist-info/METADATA
gamepadx-1.0.1.dist-info/WHEEL
gamepadx-1.0.1.dist-info/top_level.txt
gamepadx-1.0.1.dist-info/RECORD
