Metadata-Version: 2.1
Name: gamepadx
Version: 1.0.1
Summary: Read and emulate an Xbox controller
Author-email: Foralich <76852996+foralich@users.noreply.github.com>
Project-URL: Bug Tracker, https://github.com/foralich/gamepadx/issues
Project-URL: Source, https://github.com/foralich/gamepadx
Classifier: Programming Language :: Python :: 3
Classifier: License :: OSI Approved :: MIT License
Classifier: Operating System :: Microsoft :: Windows
Requires-Python: >=3.11
License-File: LICENSE
